formatter_sql_script.py
formatter_sql_script-0.2.dist-info/METADATA
formatter_sql_script-0.2.dist-info/WHEEL
formatter_sql_script-0.2.dist-info/top_level.txt
formatter_sql_script-0.2.dist-info/RECORD
