Metadata-Version: 2.1
Name: formatter-sql-script
Version: 0.2
Summary: Formateador de texto a sentencia insert de SQL
Author: Felipe Medel
Author-email: luispipemedel@gmail.com
License: MIT
Keywords: helper,sql Formatter,testing,dev
